accretive/__init__.py
accretive/classes.py
accretive/dictionaries.py
accretive/exceptions.py
accretive/iclasses.py
accretive/modules.py
accretive/namespaces.py
accretive/py.typed
accretive/__/__init__.py
accretive/__/dictionaries.py
accretive/__/doctab.py
accretive/__/exceptions.py
accretive/__/imports.py
accretive/__/nomina.py
accretive/_typedecls/__builtins__.pyi
accretive-4.2.1.dist-info/METADATA
accretive-4.2.1.dist-info/WHEEL
accretive-4.2.1.dist-info/licenses/LICENSE.txt
accretive-4.2.1.dist-info/RECORD
